cumplo_common/__init__.py
cumplo_common/database/__init__.py
cumplo_common/database/firestore/__init__.py
cumplo_common/database/firestore/channels.py
cumplo_common/database/firestore/filters.py
cumplo_common/database/firestore/notifications.py
cumplo_common/database/firestore/subcollections.py
cumplo_common/database/firestore/users.py
cumplo_common/dependencies/__init__.py
cumplo_common/dependencies/authentication.py
cumplo_common/dependencies/authorization.py
cumplo_common/integrations/__init__.py
cumplo_common/integrations/cloud_pubsub.py
cumplo_common/integrations/cloud_tasks.py
cumplo_common/middlewares/__init__.py
cumplo_common/middlewares/pubsub.py
cumplo_common/models/__init__.py
cumplo_common/models/base_model.py
cumplo_common/models/borrower.py
cumplo_common/models/channel.py
cumplo_common/models/credentials.py
cumplo_common/models/credit.py
cumplo_common/models/currency.py
cumplo_common/models/debtor.py
cumplo_common/models/filter_configuration.py
cumplo_common/models/funding_request.py
cumplo_common/models/notification.py
cumplo_common/models/pydantic.py
cumplo_common/models/simulation.py
cumplo_common/models/subject.py
cumplo_common/models/template.py
cumplo_common/models/user.py
cumplo_common/py.typed
cumplo_common/utils/__init__.py
cumplo_common/utils/constants.py
cumplo_common/utils/currency.py
cumplo_common/utils/text.py
cumplo_common-1.1.0.dist-info/LICENSE
cumplo_common-1.1.0.dist-info/METADATA
cumplo_common-1.1.0.dist-info/WHEEL
cumplo_common-1.1.0.dist-info/RECORD
