Metadata-Version: 2.1
Name: cumplo-common
Version: 1.1.0
Summary: A one-stop library that centralizes the core logic and protects the domain of the Cumplo API project
Author: Cristobal Sfeir
Author-email: hello@crisotbalsfeir.com
Requires-Python: >=3.11,<4.0
Classifier: Programming Language :: Python :: 3
Classifier: Programming Language :: Python :: 3.11
Requires-Dist: arrow (>=1.2.3,<2.0.0)
Requires-Dist: babel (>=2.12.1,<3.0.0)
Requires-Dist: fastapi (>=0.109.1,<0.110.0)
Requires-Dist: firebase-admin (>=6.2.0,<7.0.0)
Requires-Dist: google-cloud-pubsub (>=2.18.4,<3.0.0)
Requires-Dist: google-cloud-tasks (>=2.14.1,<3.0.0)
Requires-Dist: pydantic (>=2.1.1,<3.0.0)
Requires-Dist: python-dotenv (>=1.0.0,<2.0.0)
Requires-Dist: types-protobuf (>=4.23.0.2,<5.0.0.0)
Requires-Dist: ulid-py (>=1.1.0,<2.0.0)
